matplotlib_colorbar/__init__.py
matplotlib_colorbar/_version.py
matplotlib_colorbar/colorbar.py
tests/__init__.py
tests/test_colorbar.py
matplotlib_colorbar-0.4.0.dist-info/LICENSE
matplotlib_colorbar-0.4.0.dist-info/METADATA
matplotlib_colorbar-0.4.0.dist-info/WHEEL
matplotlib_colorbar-0.4.0.dist-info/top_level.txt
matplotlib_colorbar-0.4.0.dist-info/zip-safe
matplotlib_colorbar-0.4.0.dist-info/RECORD
