Metadata-Version: 1.2
Name: matplotlib-colorbar
Version: 0.4.0
Summary: Artist for matplotlib to display a color bar
Home-page: https://github.com/ppinard/matplotlib-colorbar
Author: Philippe Pinard
Author-email: philippe.pinard@gmail.com
Maintainer: Philippe Pinard
Maintainer-email: philippe.pinard@gmail.com
License: BSD
Keywords: matplotlib color bar image
Platform: UNKNOWN
Classifier: Development Status :: 4 - Beta
Classifier: Intended Audience :: Science/Research
Classifier: License :: OSI Approved :: MIT License
Classifier: Operating System :: OS Independent
Classifier: Programming Language :: Python :: 2
Classifier: Programming Language :: Python :: 3
Classifier: Topic :: Scientific/Engineering :: Visualization
